README
hello.py
pdbrc_sample
setup.py
vimpdbhook/__init__.py
vimpdbhook/activate.scr
vimpdbhook.egg-info/PKG-INFO
vimpdbhook.egg-info/SOURCES.txt
vimpdbhook.egg-info/dependency_links.txt
vimpdbhook.egg-info/entry_points.txt
vimpdbhook.egg-info/not-zip-safe
vimpdbhook.egg-info/requires.txt
vimpdbhook.egg-info/top_level.txt