Metadata-Version: 1.0
Name: vimpdbhook
Version: 0.2
Summary: A PDB hook for MacVIM
Home-page: https://vimpdbhook.googlecode.com/svn/trunk
Author: Stefan ELetzhofer
Author-email: stefan.eletzhofer@inquant.de
License: BSD
Platform: UNKNOWN
